alpacalert/__init__.py
alpacalert/generic.py
alpacalert/instrumentor.py
alpacalert/models.py
alpacalert/transform.py
alpacalert/instrumentors/__init__.py
alpacalert/instrumentors/alertmanager_models.py
alpacalert/instrumentors/grafana.py
alpacalert/instrumentors/grafana_models.py
alpacalert/instrumentors/k8s.py
alpacalert/instrumentors/prometheus.py
alpacalert/instrumentors/prometheus_models.py
alpacalert/visualisers/__init__.py
alpacalert/visualisers/console.py
alpacalert-0.1.0.dist-info/METADATA
alpacalert-0.1.0.dist-info/WHEEL
alpacalert-0.1.0.dist-info/top_level.txt
alpacalert-0.1.0.dist-info/RECORD
